{
  "node_modules/@sveltejs/kit/src/runtime/client/start.js": {
    "file": "_app/immutable/start-8eb4aa0f.js",
    "src": "node_modules/@sveltejs/kit/src/runtime/client/start.js",
    "isEntry": true,
    "imports": [
      "_preload-helper-aa6bc0ce.js",
      "_index-6a903410.js",
      "_singletons-793df22e.js"
    ],
    "dynamicImports": [
      ".svelte-kit/generated/nodes/0.js",
      ".svelte-kit/generated/nodes/1.js",
      ".svelte-kit/generated/nodes/2.js"
    ]
  },
  "node_modules/@sveltejs/kit/src/runtime/components/layout.svelte": {
    "file": "_app/immutable/components/layout.svelte-0d3dbdca.js",
    "src": "node_modules/@sveltejs/kit/src/runtime/components/layout.svelte",
    "isEntry": true,
    "imports": [
      "_index-6a903410.js"
    ]
  },
  "node_modules/@sveltejs/kit/src/runtime/components/error.svelte": {
    "file": "_app/immutable/components/error.svelte-efd5c386.js",
    "src": "node_modules/@sveltejs/kit/src/runtime/components/error.svelte",
    "isEntry": true,
    "imports": [
      "_index-6a903410.js",
      "_singletons-793df22e.js"
    ]
  },
  "src/routes/+page.svelte": {
    "file": "_app/immutable/components/pages/_page.svelte-6592916e.js",
    "src": "src/routes/+page.svelte",
    "isEntry": true,
    "imports": [
      "_index-6a903410.js",
      "_preload-helper-aa6bc0ce.js"
    ],
    "dynamicImports": [
      "node_modules/codejar/codejar.js",
      "_prism-1372a240.js"
    ],
    "css": [
      "_app/immutable/assets/_page-f72a90bf.css"
    ]
  },
  "src/routes/+layout.js": {
    "file": "_app/immutable/modules/pages/_layout.js-7b9cbfbc.js",
    "src": "src/routes/+layout.js",
    "isEntry": true,
    "imports": [
      "__layout-8d2a742b.js"
    ]
  },
  "_singletons-793df22e.js": {
    "file": "_app/immutable/chunks/singletons-793df22e.js",
    "imports": [
      "_index-6a903410.js"
    ]
  },
  "_preload-helper-aa6bc0ce.js": {
    "file": "_app/immutable/chunks/preload-helper-aa6bc0ce.js"
  },
  "_index-6a903410.js": {
    "file": "_app/immutable/chunks/index-6a903410.js"
  },
  "__layout-8d2a742b.js": {
    "file": "_app/immutable/chunks/_layout-8d2a742b.js"
  },
  ".svelte-kit/generated/nodes/0.js": {
    "file": "_app/immutable/chunks/0-f980f9e6.js",
    "src": ".svelte-kit/generated/nodes/0.js",
    "isDynamicEntry": true,
    "imports": [
      "__layout-8d2a742b.js",
      "node_modules/@sveltejs/kit/src/runtime/components/layout.svelte"
    ]
  },
  ".svelte-kit/generated/nodes/1.js": {
    "file": "_app/immutable/chunks/1-b4864d40.js",
    "src": ".svelte-kit/generated/nodes/1.js",
    "isDynamicEntry": true,
    "imports": [
      "node_modules/@sveltejs/kit/src/runtime/components/error.svelte"
    ]
  },
  ".svelte-kit/generated/nodes/2.js": {
    "file": "_app/immutable/chunks/2-f058acb7.js",
    "src": ".svelte-kit/generated/nodes/2.js",
    "isDynamicEntry": true,
    "imports": [
      "src/routes/+page.svelte"
    ]
  },
  "node_modules/codejar/codejar.js": {
    "file": "_app/immutable/chunks/codejar-f2b93de5.js",
    "src": "node_modules/codejar/codejar.js",
    "isDynamicEntry": true
  },
  "_prism-1372a240.js": {
    "file": "_app/immutable/chunks/prism-1372a240.js",
    "isDynamicEntry": true
  },
  "src/routes/+page.css": {
    "file": "_app/immutable/assets/_page-f72a90bf.css",
    "src": "src/routes/+page.css"
  }
}